README
setup.py
src/django_feedburner/__init__.py
src/django_feedburner/models.py
src/django_feedburner/testsettings.py
src/django_feedburner/views.py
src/django_feedburner.egg-info/PKG-INFO
src/django_feedburner.egg-info/SOURCES.txt
src/django_feedburner.egg-info/dependency_links.txt
src/django_feedburner.egg-info/requires.txt
src/django_feedburner.egg-info/top_level.txt
src/django_feedburner/tests/__init__.py
src/django_feedburner/tests/feeds.py
src/django_feedburner/tests/urls.py