Metadata-Version: 1.0
Name: django-feedburner
Version: 0.9.0
Summary: Handles redirection of django feeds to feedburner urls.
Home-page: https://launchpad.net/django-feedburner
Author: Gregor Müllegger
Author-email: gregor@muellegger.de
License: BSD
Platform: UNKNOWN
Classifier: Development Status :: 4 - Beta
Classifier: Environment :: Web Environment
Classifier: Framework :: Django
Classifier: Intended Audience :: Developers
Classifier: License :: OSI Approved :: BSD License
Classifier: Natural Language :: English
Classifier: Operating System :: OS Independent
Classifier: Programming Language :: Python
